[
	{
		"__TYPE__": "SharedSliceContent",
		"variation": "default",
		"primary": {
			"heading": {
				"__TYPE__": "StructuredTextContent",
				"value": [
					{
						"type": "heading2",
						"content": {
							"text": "Condition"
						}
					}
				]
			},
			"body": {
				"__TYPE__": "StructuredTextContent",
				"value": [
					{
						"type": "paragraph",
						"content": {
							"text": "Officia ad ex dolor aliquip est magna cupidatat culpa."
						}
					}
				]
			},
			"image": {
				"origin": {
					"id": "main",
					"url": "https://images.unsplash.com/photo-1587653915936-5623ea0b949a",
					"width": 4000,
					"height": 4000
				},
				"url": "https://images.unsplash.com/photo-1587653915936-5623ea0b949a",
				"width": 4000,
				"height": 4000,
				"edit": {
					"zoom": 1,
					"crop": {
						"x": 0,
						"y": 0
					},
					"background": "transparent"
				},
				"alt": "might",
				"credits": null,
				"__TYPE__": "ImageContent",
				"thumbnails": {}
			}
		},
		"items": []
	},
	{
		"__TYPE__": "SharedSliceContent",
		"variation": "imageRight",
		"primary": {
			"heading": {
				"__TYPE__": "StructuredTextContent",
				"value": [
					{
						"type": "heading2",
						"content": {
							"text": "Common"
						}
					}
				]
			},
			"body": {
				"__TYPE__": "StructuredTextContent",
				"value": [
					{
						"type": "paragraph",
						"content": {
							"text": "Voluptate ullamco laborum culpa. Consectetur id Lorem Lorem pariatur laboris amet irure laboris. Adipisicing ullamco consectetur consequat ut proident proident ad."
						}
					}
				]
			},
			"image": {
				"origin": {
					"id": "main",
					"url": "https://images.unsplash.com/photo-1537498425277-c283d32ef9db",
					"width": 4380,
					"height": 2895
				},
				"url": "https://images.unsplash.com/photo-1537498425277-c283d32ef9db",
				"width": 4380,
				"height": 2895,
				"edit": {
					"zoom": 1,
					"crop": {
						"x": 0,
						"y": 0
					},
					"background": "transparent"
				},
				"alt": "yourself",
				"credits": null,
				"__TYPE__": "ImageContent",
				"thumbnails": {}
			}
		},
		"items": [
			{
				"__TYPE__": "GroupItemContent",
				"value": []
			}
		]
	}
]